twos/__init__.py
twos/twos.py
twos-0.0.1.dist-info/METADATA
twos-0.0.1.dist-info/WHEEL
twos-0.0.1.dist-info/top_level.txt
twos-0.0.1.dist-info/RECORD
