Metadata-Version: 2.4
Name: twos
Version: 0.0.1
Summary: Interpreting integer bit patterns as two's complement or unsigned representation
Author-email: Simon Nieswand <simon.nieswand@gmail.com>
License: GPL-3.0-only
Project-URL: Homepage, https://github.com/nieswand/twos
Project-URL: Repository, https://github.com/nieswand/twos
Project-URL: Issues, https://github.com/nieswand/twos/issues
Classifier: Programming Language :: Python :: 3
Requires-Python: >=3.7
